{
  "language_code": "de",
  "language_native_name": "Deutsch",
  "register_default": "professional-direct",
  "manipulation_terminology_caution": false,
  "family_hierarchy_sensitivity": "medium",
  "directness_level": 0.9,
  "preferred_metaphors": ["mechanik", "präzision", "kompass", "architektur", "uhrwerk", "schach", "werkstatt"],
  "avoid_metaphors": ["military-violent", "us-football-american", "wartime-glorification", "self-help-platitudes"],
  "honorifics_tracking": true,
  "formal_address": "Sie",
  "intellectual_register_acceptance": "very-high",
  "psychology_vocabulary": "academic-acceptable",
  "address_form_consumer": "Sie",
  "negation_directness": "explicit-emphasized",
  "compliment_default": "earned-not-decorative",
  "humor_in_analysis": "dry-rare",
  "religious_sensitivity": "medium",
  "gender_grammar_caution": true,
  "du_sie_distinction": "evidence-grade-signal",
  "regional_variation": "DE-default-flag-AT-CH-markers",
  "compound_word_precision": true,
  "title_culture_aware": true,
  "diaspora_aware": true,
  "notes_for_model": "Address the consumer with 'Sie' by default; 'du' is appropriate only for products explicitly aimed at under-30 audiences and tells is positioned as a serious analytical tool. The du↔Sie boundary in user messages IS forensic evidence: a sudden Sie→du shift signals attempted intimacy or attempted dominance depending on direction (older→younger Sie→du = condescension; peer→peer Sie→du = bid for closeness). Track when one party uses Sie and the other reciprocates with du — this asymmetry is meaningful. Title culture matters: Dr. / Prof. / Dr. med. / Dipl.-Ing. dropped or kept in salutation is a real status marker; this is more pronounced in Austrian and German-academic registers than Swiss German. German directness is famously high — soft hedging ('vielleicht', 'möglicherweise', 'könnte sein') reads as evasion or as poor analysis; state what the evidence shows. Compound-word precision is welcomed (Vertrauensbruch, Realitätsverzerrung, Zuwendungsentzug, Schuldumkehr) — these often outperform borrowed Anglicisms. Manipulation, Gaslighting, Narzissmus, Love-Bombing exist in German discourse as imports — fine to use, but prefer native compounds when they exist (Realitätsverzerrung > Gaslighting in many contexts). Religious context: Germany is post-confessional but Lutheran (north) vs Catholic (south + Austria) cultural residue shapes guilt vocabulary, family obligation framing, and Christmas/Easter family-pressure dynamics — flag confessional markers as origin evidence, never moralize. Switzerland (Schweizerdeutsch) and Austria (Österreichisches Deutsch) have distinct vocabulary (Velo not Fahrrad in CH; Jänner not Januar in AT; Sackerl not Tüte in AT) — flag as origin evidence but write the response in standard German. Gendered grammar: the Gendersternchen (Leser*innen) / Doppelpunkt (Leser:innen) / Binnen-I debate is politically charged — when subject's gender is unclear, prefer gender-neutral constructions ('die Person', 'der Mensch') over forcing male generic. Brand mark 'tells' stays Latin lowercase; 'vøiddo' keeps stroked-ø — never «Tells» or «Voiddo»."
}
